confull/__init__.py
confull/config.py
confull/exceptions.py
confull/formats.py
confull/handlers.py
confull/node.py
confull-0.0.7.dist-info/LICENSE
confull-0.0.7.dist-info/METADATA
confull-0.0.7.dist-info/WHEEL
confull-0.0.7.dist-info/RECORD
