Metadata-Version: 2.3
Name: confull
Version: 0.0.7
Summary: 一个简单的配置管理工具(A simple dictionary configuration management tool),dict <-> config file [json, toml, yaml, ini, xml]
License: MIT
Keywords: configuration,toml,yaml,json,ini,xml
Author: zisul
Author-email: zisull@qq.com
Requires-Python: >=3.6,<4.0
Classifier: License :: OSI Approved :: MIT License
Classifier: Operating System :: OS Independent
Classifier: Programming Language :: Python :: 3
Classifier: Programming Language :: Python :: 3.6
Classifier: Programming Language :: Python :: 3.7
Classifier: Programming Language :: Python :: 3.8
Classifier: Programming Language :: Python :: 3.9
Classifier: Programming Language :: Python :: 3.10
Classifier: Programming Language :: Python :: 3.11
Classifier: Programming Language :: Python :: 3.12
Classifier: Programming Language :: Python :: 3.13
Classifier: Topic :: Software Development :: Libraries
Requires-Dist: PyYAML (>=6.0.2,<7.0.0)
Requires-Dist: configparser (>=7.1.0,<8.0.0)
Requires-Dist: cryptography (>=42.0.0,<43.0.0)
Requires-Dist: orjson (>=3.10.11,<4.0.0)
Requires-Dist: portalocker (>=3.0.0,<4.0.0)
Requires-Dist: toml (>=0.10.2,<0.11.0)
Requires-Dist: watchdog (>=3.0.0,<4.0.0)
